aiogram2252_page/__init__.py
aiogram2252_page/paginator.py
aiogram2252_page-0.0.4.dist-info/LICENCE
aiogram2252_page-0.0.4.dist-info/METADATA
aiogram2252_page-0.0.4.dist-info/WHEEL
aiogram2252_page-0.0.4.dist-info/top_level.txt
aiogram2252_page-0.0.4.dist-info/RECORD
