Metadata-Version: 2.1
Name: aiogram2252_page
Version: 0.0.4
Summary: Inline pagination for aiogram 2.25.2
Author-email: llimonix <llimonix123@yandex.com>
Project-URL: Homepage, https://github.com/llimonix/aiogram-pagination-inline-2.25.2
Project-URL: Issues, https://github.com/llimonix/aiogram-pagination-inline-2.25.2/issues
Classifier: Programming Language :: Python :: 3.11
Classifier: License :: OSI Approved :: MIT License
Classifier: Operating System :: OS Independent
Requires-Python: >=3.11
License-File: LICENCE
